pytestreport/__init__.py
pytestreport/reporter.py
pytestreport_md-0.1.5.dist-info/LICENSE
pytestreport_md-0.1.5.dist-info/METADATA
pytestreport_md-0.1.5.dist-info/WHEEL
pytestreport_md-0.1.5.dist-info/top_level.txt
pytestreport_md-0.1.5.dist-info/RECORD
