Metadata-Version: 2.1
Name: pytestreport-md
Version: 0.1.5
Summary: Uma biblioteca para gerar relatórios de teste com emojis
Author-email: Hedris Pereira <hedrisgts@gmail.com>
License: MIT
Project-URL: Repository, https://github.com/Hedriss10/pytest-report/tree/main
Keywords: pytest,report,emojis
Classifier: Programming Language :: Python :: 3
Classifier: License :: OSI Approved :: MIT License
Classifier: Operating System :: OS Independent
License-File: LICENSE
